{"stat.walkOneCm":15404,"achievement.openInventory":2,"stat.leaveGame":3,"stat.damageTaken":220,"stat.killEntity.Wolf":1,"stat.mobKills":1,"stat.mineBlock.minecraft.log":7,"stat.flyOneCm":9289,"stat.jump":90,"stat.mineBlock.minecraft.leaves":4,"stat.playOneMinute":7874,"stat.fallOneCm":6750,"stat.useItem.minecraft.cooked_beef":1,"stat.damageDealt":80,"stat.timeSinceDeath":7874,"achievement.mineWood":6,"stat.useItem.minecraft.dirt":2,"stat.sprintOneCm":6200,"stat.mineBlock.minecraft.dirt":13,"achievement.exploreAllBiomes":{"value":0,"progress":["Forest"]}}